aio_executor.py
aio_executor-0.2.0.dist-info/LICENSE
aio_executor-0.2.0.dist-info/METADATA
aio_executor-0.2.0.dist-info/WHEEL
aio_executor-0.2.0.dist-info/top_level.txt
aio_executor-0.2.0.dist-info/RECORD
