Metadata-Version: 2.1
Name: aio-executor
Version: 0.2.0
Summary: A concurrent.futures.Executor implementation that runs asynchronous tasks in an asyncio event loop.
Home-page: http://github.com/miguelgrinberg/aio-executor/
Author: Miguel Grinberg
Author-email: miguel.grinberg@gmail.com
License: MIT
Platform: any
Classifier: Framework :: AsyncIO
Classifier: Intended Audience :: Developers
Classifier: License :: OSI Approved :: MIT License
Classifier: Operating System :: OS Independent
Classifier: Programming Language :: Python
Classifier: Programming Language :: Python :: 3
Classifier: Topic :: Software Development :: Libraries :: Python Modules
Requires-Python: >=3.7
